heater/__init__.py
heater/__main__.py
heater/heater.py
heater/resources/__init__.py
heater/resources/dot.png
heater/resources/scale.png
heater-0.0.1.dist-info/WHEEL
heater-0.0.1.dist-info/METADATA
heater-0.0.1.dist-info/RECORD
